ucxx/GIT_COMMIT
ucxx/VERSION
ucxx/__init__.py
ucxx/_version.py
ucxx/core.py
ucxx/exceptions.py
ucxx/testing.py
ucxx/types.py
ucxx/utils.py
ucxx/_lib/__init__.pxd
ucxx/_lib/__init__.py
ucxx/_lib/arr.cpython-313-x86_64-linux-gnu.so
ucxx/_lib/arr.pxd
ucxx/_lib/arr.pyi
ucxx/_lib/libucxx.cpython-313-x86_64-linux-gnu.so
ucxx/_lib/libucxx.pxd
ucxx/_lib/ucxx_api.pxd
ucxx/_lib_async/__init__.py
ucxx/_lib_async/application_context.py
ucxx/_lib_async/continuous_ucx_progress.py
ucxx/_lib_async/endpoint.py
ucxx/_lib_async/exchange_peer_info.py
ucxx/_lib_async/listener.py
ucxx/_lib_async/notifier_thread.py
ucxx/_lib_async/utils.py
ucxx/_lib_async/utils_test.py
ucxx/benchmarks/__init__.py
ucxx/benchmarks/asyncssh.py
ucxx/benchmarks/cudf_merge.py
ucxx/benchmarks/send_recv.py
ucxx/benchmarks/utils.py
ucxx/benchmarks/backends/__init__.py
ucxx/benchmarks/backends/asyncio.py
ucxx/benchmarks/backends/base.py
ucxx/benchmarks/backends/socket.py
ucxx/benchmarks/backends/tornado.py
ucxx/benchmarks/backends/ucxx_async.py
ucxx/benchmarks/backends/ucxx_core.py
ucxx/examples/__init__.pxd
ucxx/examples/__init__.py
ucxx/examples/python_future_task.h
ucxx/examples/python_future_task_api.pxd
ucxx/examples/python_future_task_app.cpython-313-x86_64-linux-gnu.so
ucxx/examples/python_future_task_example.py
ucxx/include/ucxx/python/api.h
ucxx/include/ucxx/python/constructors.h
ucxx/include/ucxx/python/exception.h
ucxx/include/ucxx/python/future.h
ucxx/include/ucxx/python/notifier.h
ucxx/include/ucxx/python/python_future.h
ucxx/include/ucxx/python/python_future_task.h
ucxx/include/ucxx/python/python_future_task_collector.h
ucxx/include/ucxx/python/worker.h
ucxx/lib64/libucxx_python.so
ucxx/lib64/cmake/ucxx-python/ucxx-python-config-version.cmake
ucxx/lib64/cmake/ucxx-python/ucxx-python-config.cmake
ucxx/lib64/cmake/ucxx-python/ucxx-python-dependencies.cmake
ucxx/lib64/cmake/ucxx-python/ucxx-python-targets-release.cmake
ucxx_cu12-0.47.0.dist-info/METADATA
ucxx_cu12-0.47.0.dist-info/WHEEL
ucxx_cu12-0.47.0.dist-info/entry_points.txt
ucxx_cu12-0.47.0.dist-info/RECORD
ucxx_cu12-0.47.0.dist-info/licenses/LICENSE
